dash_feature_impact/AGGridFeatureTable.py
dash_feature_impact/ConnectingLine.py
dash_feature_impact/DashFeatureImpact.css
dash_feature_impact/DashFeatureImpact.py
dash_feature_impact/FeatureTable.py
dash_feature_impact/ForcePlot.py
dash_feature_impact/KDEPlot.py
dash_feature_impact/__init__.py
dash_feature_impact/_imports_.py
dash_feature_impact/dash_feature_impact.min.js
dash_feature_impact/dash_feature_impact.min.js.map
dash_feature_impact/metadata.json
dash_feature_impact/package-info.json
dash_feature_impact-0.0.1.dist-info/LICENSE
dash_feature_impact-0.0.1.dist-info/METADATA
dash_feature_impact-0.0.1.dist-info/WHEEL
dash_feature_impact-0.0.1.dist-info/top_level.txt
dash_feature_impact-0.0.1.dist-info/RECORD
