Metadata-Version: 2.2
Name: dash_feature_impact
Version: 0.0.1
Summary: A Dash component library for visualizing machine learning feature importance and impact. Create intuitive, interactive visualizations that show how individual features contribute to model predictions. Includes force plot visualizations that display feature contributions alongside prediction distributions, helping users understand how each variable drives model outputs. Ideal for model interpretation, debugging, and explaining predictions to stakeholders.
Author: Evan Rasmussen <evanras@umich.edu>
License: MIT
Classifier: Framework :: Dash
License-File: LICENSE
Dynamic: author
Dynamic: classifier
Dynamic: description
Dynamic: description-content-type
Dynamic: license
Dynamic: summary
